parallex/__init__.py
parallex/ai/batch_processor.py
parallex/ai/open_ai_client.py
parallex/ai/output_processor.py
parallex/ai/uploader.py
parallex/file_management/converter.py
parallex/file_management/file_finder.py
parallex/file_management/remote_file_handler.py
parallex/file_management/utils.py
parallex/models/batch_file.py
parallex/models/image_file.py
parallex/models/page_response.py
parallex/models/parallex_callable_output.py
parallex/models/parallex_prompts_callable_output.py
parallex/models/prompt_response.py
parallex/models/raw_file.py
parallex/models/upload_batch.py
parallex/parallex.py
parallex/utils/constants.py
parallex/utils/logger.py
parallex-0.5.0.dist-info/LICENSE
parallex-0.5.0.dist-info/METADATA
parallex-0.5.0.dist-info/WHEEL
parallex-0.5.0.dist-info/RECORD
