Metadata-Version: 2.1
Name: parallex
Version: 0.5.0
Summary: PDF to markdown using Azure OpenAI batch processing
Home-page: https://github.com/Summed-AI/parallex
Author: Jeff Hostetler
Author-email: jeff@summed.ai
Requires-Python: >=3.12,<4.0
Classifier: Programming Language :: Python :: 3
Classifier: Programming Language :: Python :: 3.12
Classifier: Programming Language :: Python :: 3.13
Requires-Dist: aiologger (>=0.7.0,<0.8.0)
Requires-Dist: asyncio (>=3.4.3,<4.0.0)
Requires-Dist: httpx (>=0.27.2,<0.28.0)
Requires-Dist: openai (>=1.54.4,<2.0.0)
Requires-Dist: pdf2image (>=1.17.0,<2.0.0)
Requires-Dist: pydantic (>=2.9.2,<3.0.0)
Project-URL: Repository, https://github.com/Summed-AI/parallex
